gdb_mi/__init__.py
gdb_mi/version.py
python_gdb_mi-2.0.1.data/data/LICENSE
python_gdb_mi-2.0.1.dist-info/LICENSE
python_gdb_mi-2.0.1.dist-info/METADATA
python_gdb_mi-2.0.1.dist-info/WHEEL
python_gdb_mi-2.0.1.dist-info/top_level.txt
python_gdb_mi-2.0.1.dist-info/RECORD
