Metadata-Version: 2.1
Name: python-gdb-mi
Version: 2.0.1
Summary: A parser for GDB Machine Interface (MI) events.
Home-page: https://bad-address.github.io
Author: Di Paola Martin
Author-email: use-github-issues@example.com
License: GNU LGPLv3
Keywords: debugger gdb
Platform: UNKNOWN
Classifier: Development Status :: 5 - Production/Stable
Classifier: Intended Audience :: Developers
Classifier: Topic :: Software Development :: Debuggers
Classifier: License :: OSI Approved :: GNU Lesser General Public License v3 (LGPLv3)
Classifier: Programming Language :: Python :: 3
Requires-Python: >=3.5
